django_quotas/__init__.py
django_quotas/apps.py
django_quotas/backends/__init__.py
django_quotas/backends/db/__init__.py
django_quotas/backends/db/admin.py
django_quotas/backends/db/apps.py
django_quotas/backends/db/base_models.py
django_quotas/backends/db/config.py
django_quotas/backends/db/migrations/0001_initial.py
django_quotas/backends/db/migrations/__init__.py
django_quotas/backends/db/models.py
django_quotas/backends/db/service.py
django_quotas/base/__init__.py
django_quotas/base/dto.py
django_quotas/base/features.py
django_quotas/base/service.py
django_quotas/config.py
django_quotas/defaults/__init__.py
django_quotas/defaults/admin.py
django_quotas/defaults/apps.py
django_quotas/defaults/migrations/0001_initial.py
django_quotas/defaults/migrations/__init__.py
django_quotas/defaults/models.py
django_quotas/models.py
django_quotas/py.typed
django_quotas/utils.py
django_quotas-1.0.0.dist-info/LICENSE
django_quotas-1.0.0.dist-info/METADATA
django_quotas-1.0.0.dist-info/WHEEL
django_quotas-1.0.0.dist-info/RECORD
