Metadata-Version: 2.3
Name: django-quotas
Version: 1.0.0
Summary: 
License: MIT
Keywords: django,plans,accounts,quota
Author: Dmitry Berezovsky
Author-email: django-quotas-dev@googlegroups.com
Requires-Python: >=3.11,<4.0
Classifier: Development Status :: 3 - Alpha
Classifier: Intended Audience :: Developers
Classifier: License :: OSI Approved :: Apache Software License
Classifier: Operating System :: OS Independent
Classifier: Programming Language :: Python :: 3.11
Classifier: Programming Language :: Python :: 3.12
Classifier: Topic :: Software Development :: Libraries :: Python Modules
Requires-Dist: django (>=5.0.0)
Project-URL: Repository, https://github.com/corvis/django-quotas
